Workbook
Name supplier_usd: Inputs!$B$2
Name usd_rub: Inputs!$B$3
Name usd_local: Inputs!$B$4
Name fx_fees: Inputs!$B$5
Name freight_ru_rub: Inputs!$B$6
Name duty: Inputs!$B$7
Name vat_ru: Inputs!$B$8
Name pack_rub: Inputs!$B$9
Name ru_price: Inputs!$B$10
Name ru_comm: Inputs!$B$11
Name ru_logi: Inputs!$B$12
Name acq: Inputs!$B$13
Name ads: Inputs!$B$14
Name vat_base_share: Inputs!$B$15
Name fe_price_rub: Inputs!$B$16
Name fe_comm: Inputs!$B$17
Name fe_logi_rub: Inputs!$B$18
Name fe_freight_rub: Inputs!$B$19
Name fe_vat_import: Inputs!$B$20
Name fe_ru_vat_on_top: Inputs!$B$21
Name fe_fixed_per_unit_rub: Inputs!$B$22
Name cb_price_rub: Inputs!$B$23
Name cb_platform_fee: Inputs!$B$24
Name cb_parcel_rub: Inputs!$B$25
Name cb_duty_share: Inputs!$B$26
Name own_price_rub: Inputs!$B$27
Name own_delivery_rub: Inputs!$B$28
Name own_return_share: Inputs!$B$29
Name own_cac_1: Inputs!$B$30
Name own_cac_2: Inputs!$B$31
Name own_cac_3: Inputs!$B$32
Name target_margin: Inputs!$B$33

Sheet README
A1: DemoBrand - unit economics by sales channel (ILLUSTRATIVE, synthetic numbers).
A2: Yellow cells on 'Inputs' are assumptions; everything else recalculates with formulas.
A3: Margin = per bought-out unit, before profit tax. Tax/customs logic is simplified - verify before use.
A4: Sheets: RU_FBO (base), Foreign_entity (a foreign company sells to RU buyers), Crossborder, OwnStore (3 CAC scenarios), Compare.
A5: The Compare sheet only reflects the synthetic inputs - it is not a conclusion about any real channel.

Sheet Inputs
A1: key | B1: value | C1: description
A2: supplier_usd | B2: 4.8 | C2: Supplier price per unit, USD (synthetic)
A3: usd_rub | B3: 90 | C3: USD/RUB rate used in the model (illustrative)
A4: usd_local | B4: 480 | C4: USD to foreign-entity local currency rate (illustrative)
A5: fx_fees | B5: 0.03 | C5: Bank + payment agent + FX markup, share of purchase
A6: freight_ru_rub | B6: 45 | C6: Freight to RU warehouse per unit, RUB
A7: duty | B7: 0.065 | C7: Import duty rate (illustrative)
A8: vat_ru | B8: 0.22 | C8: VAT rate RU (verify current law)
A9: pack_rub | B9: 25 | C9: Packaging / labelling per unit, RUB
A10: ru_price | B10: 1990 | C10: RU marketplace seller price, RUB
A11: ru_comm | B11: 0.28 | C11: RU marketplace commission (FBO), share
A12: ru_logi | B12: 95 | C12: RU marketplace logistics per unit, RUB
A13: acq | B13: 0.015 | C13: Acquiring / payment processing, share
... A33: target_margin | B33: 0.15 | C33: Target margin share used for the 'price needed' line

Sheet RU_FBO
A1: RU marketplace, FBO (base case)
A2: Line | B2: RUB per unit | C2: Formula logic
A3: Purchase, RUB | B3: =supplier_usd*usd_rub*(1+fx_fees) | C3: supplier price x FX x (1 + bank/agent/FX fees)
A4: Freight to RU | B4: =freight_ru_rub | C4: input
A5: Duty | B5: =(B3+B4)*duty | C5: (purchase + freight) x duty
A6: Packaging | B6: =pack_rub | C6: input
A7: COGS ex import VAT | B7: =B3+B4+B5+B6 | C7: sum
A8: Import VAT (creditable) | B8: =(B3+B4+B5)*vat_ru | C8: customs value x VAT; reduces VAT payable
A9: Seller price | B9: =ru_price | C9: input
A10: Marketplace commission | B10: =B9*ru_comm | C10: price x commission
A11: Logistics | B11: =ru_logi | C11: input
A12: Acquiring | B12: =B9*acq | C12: price x rate
A13: Ads | B13: =B9*ads | C13: price x ads share
A14: VAT payable (model) | B14: =B9*vat_base_share*vat_ru/(1+vat_ru)-B8 | C14: price x base share x 22/122 - import VAT
A15: MARGIN, RUB | B15: =B9-B10-B11-B12-B13-B14-B7 | C15: price - all lines - COGS
A16: MARGIN, % of price | B16: =B15/B9
A17: Price needed for target margin | B17: =(B11+B7-B8)/(1-ru_comm-acq-ads-vat_base_share*vat_ru/(1+vat_ru)-target_margin) | C17: solves margin = target x price

Sheet Foreign_entity
A1: Foreign entity selling to RU buyers through the marketplace foreign-seller contract (simplified)
A2: Line | B2: RUB per unit | C2: Formula logic
A3: Purchase, RUB | B3: =supplier_usd*usd_rub*(1+fx_fees) | C3: same supplier price
A4: Freight to foreign warehouse | B4: =fe_freight_rub | C4: input
A5: Duty (foreign) | B5: =(B3+B4)*duty | C5: illustrative common tariff
A6: Packaging | B6: =pack_rub | C6: input
A7: COGS | B7: =B3+B4+B5+B6 | C7: sum
A8: Foreign import VAT (cash-flow only) | B8: =(B3+B4+B5)*fe_vat_import | C8: assumed creditable; shown, not deducted
A9: Seller price | B9: =fe_price_rub | C9: input
A10: RU VAT on top (paid by buyer, remitted) | B10: =B9*fe_ru_vat_on_top | C10: not seller income
A11: Marketplace commission | B11: =B9*fe_comm | C11: price x commission
A12: Logistics foreign warehouse -> RU buyer | B12: =fe_logi_rub | C12: input
A13: Acquiring + ads | B13: =B9*(acq+ads)
A14: Entity / certification costs per unit | B14: =fe_fixed_per_unit_rub | C14: amortised
A15: MARGIN, RUB | B15: =B9-B11-B12-B13-B14-B7 | C15: price - lines - COGS
A16: MARGIN, % of price | B16: =B15/B9

Sheet Crossborder
A1: Foreign company, cross-border parcels to RU buyers (simplified)
A2: Line | B2: RUB per unit | C2: Formula logic
A3: Purchase, RUB | B3: =supplier_usd*usd_rub*(1+fx_fees) | C3: same supplier price
A4: International parcel | B4: =cb_parcel_rub | C4: per unit
A5: Expected duty | B5: =cb_duty_share*B9*duty | C5: only orders above the threshold
A6: Packaging | B6: =pack_rub | C6: input
A7: COGS (landed at buyer) | B7: =B3+B4+B6 | C7: duty kept separate
A8: (no RU import VAT for the seller) | B8: 0 | C8: cross-border parcel model
A9: Price | B9: =cb_price_rub | C9: input
A10: Platform fee | B10: =B9*cb_platform_fee | C10: price x fee
A11: Acquiring + ads | B11: =B9*(acq+ads)
A12: MARGIN, RUB | B12: =B9-B10-B11-B5-B7 | C12: price - fee - acq/ads - duty - COGS
A13: MARGIN, % of price | B13: =B12/B9

Sheet OwnStore
A1: Own web store + marketplace delivery service (stock stays at the FBO warehouse)
A2: Line | B2: RUB per unit | C2: Formula logic
A3: Purchase, RUB | B3: =supplier_usd*usd_rub*(1+fx_fees) | C3: supplier price x FX x (1 + bank/agent/FX fees)
A4: Freight to RU | B4: =freight_ru_rub | C4: input
A5: Duty | B5: =(B3+B4)*duty | C5: (purchase + freight) x duty
A6: Packaging | B6: =pack_rub | C6: input
A7: COGS ex import VAT | B7: =B3+B4+B5+B6 | C7: sum
A8: Import VAT (creditable) | B8: =(B3+B4+B5)*vat_ru | C8: customs value x VAT; reduces VAT payable
A9: Price (buyer pays) | B9: =own_price_rub | C9: input
A10: Acquiring | B10: =B9*acq
A11: Delivery to pick-up point | B11: =own_delivery_rub | C11: seller pays delivery
A12: Returns: lost delivery on non-buyouts | B12: =own_return_share/(1-own_return_share)*own_delivery_rub | C12: per bought-out unit
A13: VAT payable | B13: =B9*vat_ru/(1+vat_ru)-B8 | C13: full price is the VAT base
A14: Margin before CAC | B14: =B9-B10-B11-B12-B13-B7
A15: MARGIN, CAC scenario 1 | B15: =B14-own_cac_1
A16: MARGIN, CAC scenario 2 | B16: =B14-own_cac_2
A17: MARGIN, CAC scenario 3 | B17: =B14-own_cac_3

Sheet Compare
A1: Channel | B1: Price, RUB | C1: Margin, RUB | D1: Margin, %
A2: RU FBO | B2: =RU_FBO!B9 | C2: =RU_FBO!B15 | D2: =C2/B2
A3: Foreign entity | B3: =Foreign_entity!B9 | C3: =Foreign_entity!B15 | D3: =C3/B3
A4: Cross-border | B4: =Crossborder!B9 | C4: =Crossborder!B12 | D4: =C4/B4
A5: Own store, CAC 2 | B5: =OwnStore!B9 | C5: =OwnStore!B16 | D5: =C5/B5
